{
  "id": 8415592,
  "name": "In the Matter of Nathan Allan NEAL Petition for Reinstatement from Inactive Status",
  "name_abbreviation": "In re Neal",
  "decision_date": "2006-06-20",
  "docket_number": "No. 5 DB 2006",
  "first_page": "475",
  "last_page": "476",
  "citations": [
    {
      "type": "official",
      "cite": "901 A.2d 475"
    }
  ],
  "court": {
    "name_abbreviation": "Pa.",
    "id": 8832,
    "name": "Supreme Court of Pennsylvania"
  },
  "jurisdiction": {
    "id": 6,
    "name_long": "Pennsylvania",
    "name": "Pa."
  },
  "cites_to": [],
  "analysis": {
    "cardinality": 79,
    "char_count": 784,
    "ocr_confidence": 0.684,
    "sha256": "9b05a5a970e8bad39be3f766773ab04b9e71f46e1d40ca1f2d09db4bf5431736",
    "simhash": "1:d5b0f5f99683dfbc",
    "word_count": 131
  },
  "last_updated": "2023-07-14T17:52:01.341787+00:00",
  "provenance": {
    "date_added": "2019-08-29",
    "source": "Harvard",
    "batch": "2018"
  },
  "casebody": {
    "judges": [],
    "parties": [
      "In the Matter of Nathan Allan NEAL Petition for Reinstatement from Inactive Status."
    ],
    "opinions": [
      {
        "text": "ORDER\nPER CURIAM.\nAND NOW, this 20th day of June, 2006, the Report and Recommendations of the Disciplinary Board dated May 1, 2006, are approved and it is ORDERED that Nathan Allan Neal, who has been on inactive status, has never been suspended or disbarred, and has demonstrated that he has the moral qualifications, competency and learning in law required for admission to practice in the Commonwealth, shall be and is hereby reinstated to active status as a member of the Bar of this Commonwealth. The expenses incurred by the Board in the investigation and processing of the Petition for Reinstatement shall be paid by the Petitioner.",
        "type": "majority",
        "author": "PER CURIAM."
      }
    ],
    "attorneys": [],
    "corrections": "",
    "head_matter": "In the Matter of Nathan Allan NEAL Petition for Reinstatement from Inactive Status.\nNo. 5 DB 2006.\nSupreme Court of Pennsylvania.\nJune 20, 2006."
  },
  "file_name": "0475-03",
  "first_page_order": 511,
  "last_page_order": 512
}
