{
  "id": 12501798,
  "name": "COM. v. DULIK, S.",
  "name_abbreviation": "Com. v. Dulik",
  "decision_date": "2018-07-23",
  "docket_number": "1549 WDA 2017",
  "first_page": "702",
  "last_page": "702",
  "citations": [
    {
      "type": "official",
      "cite": "194 A.3d 702"
    }
  ],
  "court": {
    "name_abbreviation": "Pa. Super. Ct.",
    "id": 8775,
    "name": "Superior Court of Pennsylvania"
  },
  "jurisdiction": {
    "id": 6,
    "name_long": "Pennsylvania",
    "name": "Pa."
  },
  "cites_to": [],
  "analysis": {
    "cardinality": 15,
    "char_count": 88,
    "sha256": "1153c832f350ac10cd84aaefe4fd0aba6b18f96ca64e1c413342868807f325d0",
    "simhash": "1:3cde0629f7f9bc46",
    "word_count": 15
  },
  "last_updated": "2021-08-27T20:57:39.405912+00:00",
  "provenance": {
    "date_added": "2021-08-27",
    "source": "Fastcase",
    "batch": "2021"
  },
  "casebody": {
    "judges": [],
    "parties": [
      "COM.\nv.\nDULIK, S."
    ],
    "opinions": [
      {
        "text": "",
        "type": "majority",
        "author": null
      }
    ],
    "attorneys": [],
    "corrections": "",
    "head_matter": "COM.\nv.\nDULIK, S.\n1549 WDA 2017\nSuperior Court of Pennsylvania.\nJuly 23, 2018\nAffirmed"
  },
  "file_name": "0702-03",
  "first_page_order": 702,
  "last_page_order": 702
}
