{
  "id": 12488331,
  "name": "In the Interest of: I.S., a Minor",
  "name_abbreviation": "In re I.S.",
  "decision_date": "2016-05-09",
  "docket_number": "1459 EDA 2015",
  "first_page": "1140",
  "last_page": "1140",
  "citations": [
    {
      "type": "official",
      "cite": "151 A.3d 1140"
    }
  ],
  "court": {
    "name_abbreviation": "Pa. Super. Ct.",
    "id": 8775,
    "name": "Superior Court of Pennsylvania"
  },
  "jurisdiction": {
    "id": 6,
    "name_long": "Pennsylvania",
    "name": "Pa."
  },
  "cites_to": [],
  "analysis": {
    "cardinality": 17,
    "char_count": 103,
    "sha256": "550d238256e2920fca86b0bb92faedc948295a6bc841e2da7976cdfa51d8538f",
    "simhash": "1:9c9b56797cee9fa8",
    "word_count": 18
  },
  "last_updated": "2021-08-27T20:57:14.008363+00:00",
  "provenance": {
    "date_added": "2021-08-27",
    "source": "Fastcase",
    "batch": "2021"
  },
  "casebody": {
    "judges": [],
    "parties": [
      "In the Interest of: I.S., a Minor"
    ],
    "opinions": [
      {
        "text": "",
        "type": "majority",
        "author": null
      }
    ],
    "attorneys": [],
    "corrections": "",
    "head_matter": "In the Interest of: I.S., a Minor\n1459 EDA 2015\nSuperior Court of Pennsylvania.\nMay 9, 2016\nAffirmed."
  },
  "file_name": "1140-13",
  "first_page_order": 1140,
  "last_page_order": 1140
}
