{
  "id": 12488538,
  "name": "Com. v. Berger, C.",
  "name_abbreviation": "Com v. Berger",
  "decision_date": "2016-05-19",
  "docket_number": "1173 WDA 2015",
  "first_page": "1153",
  "last_page": "1153",
  "citations": [
    {
      "type": "official",
      "cite": "151 A.3d 1153"
    }
  ],
  "court": {
    "name_abbreviation": "Pa. Super. Ct.",
    "id": 8775,
    "name": "Superior Court of Pennsylvania"
  },
  "jurisdiction": {
    "id": 6,
    "name_long": "Pennsylvania",
    "name": "Pa."
  },
  "cites_to": [],
  "analysis": {
    "cardinality": 17,
    "char_count": 110,
    "sha256": "51b1fd3f086f0f7676d62df30308233b0980b3a1084885adbc338e99dbfdab38",
    "simhash": "1:dcdb1682772897e9",
    "word_count": 17
  },
  "last_updated": "2021-08-27T20:57:14.008363+00:00",
  "provenance": {
    "date_added": "2021-08-27",
    "source": "Fastcase",
    "batch": "2021"
  },
  "casebody": {
    "judges": [],
    "parties": [
      "Com.\nv.\nBerger, C."
    ],
    "opinions": [
      {
        "text": "",
        "type": "majority",
        "author": null
      }
    ],
    "attorneys": [],
    "corrections": "",
    "head_matter": "Com.\nv.\nBerger, C.\n1173 WDA 2015\nSuperior Court of Pennsylvania.\nMay 19, 2016\nRemanded Jurisdiction Retained"
  },
  "file_name": "1153-15",
  "first_page_order": 1153,
  "last_page_order": 1153
}
